heatmisercontroller/__init__.py
heatmisercontroller/adaptor.py
heatmisercontroller/decorators.py
heatmisercontroller/devices_prt_e.py
heatmisercontroller/devices_prt_hw.py
heatmisercontroller/exceptions.py
heatmisercontroller/fields.py
heatmisercontroller/fields_special.py
heatmisercontroller/framing.py
heatmisercontroller/generaldevices.py
heatmisercontroller/genericdevice.py
heatmisercontroller/hm_constants.py
heatmisercontroller/hmcontroller.conf
heatmisercontroller/hmcontroller.spec
heatmisercontroller/logging_setup.py
heatmisercontroller/network.py
heatmisercontroller/observer.py
heatmisercontroller/schedule_functions.py
heatmisercontroller/setup.py
heatmisercontroller/thermostatstate.py
heatmisercontroller-0.51.data/scripts/hm_check_time_example.py
heatmisercontroller-0.51.data/scripts/hm_find_example.py
heatmisercontroller-0.51.data/scripts/hm_get_example.py
heatmisercontroller-0.51.data/scripts/hm_set_example.py
heatmisercontroller-0.51.dist-info/LICENSE
heatmisercontroller-0.51.dist-info/METADATA
heatmisercontroller-0.51.dist-info/WHEEL
heatmisercontroller-0.51.dist-info/top_level.txt
heatmisercontroller-0.51.dist-info/RECORD
