Metadata-Version: 2.1
Name: heatmisercontroller
Version: 0.51
Summary: Python implementation of Heatmiser protocol for serial connected thermostats 
Home-page: https://github.com/ianhorsley/heatmisercontroller
Author: Ian Horsley
License: GNU v3.0
Classifier: Programming Language :: Python :: 3.7
License-File: LICENSE
Requires-Dist: datetime
Requires-Dist: pyserial
Requires-Dist: configobj
Requires-Dist: transitions
